LICENSE
MANIFEST.in
README.md
setup.py
bin/prmpt
prmpt/__init__.py
prmpt/colours.py
prmpt/compiler.py
prmpt/config.py
prmpt/functionBase.py
prmpt/functionContainer.py
prmpt/functions.py
prmpt/git.py
prmpt/lexer.py
prmpt/parser.py
prmpt/prompt.py
prmpt/status.py
prmpt/svn.py
prmpt/userdir.py
prmpt/vcs.py
prmpt.egg-info/PKG-INFO
prmpt.egg-info/SOURCES.txt
prmpt.egg-info/dependency_links.txt
prmpt.egg-info/requires.txt
prmpt.egg-info/top_level.txt
prmpt/utils/__init__.py
prmpt/utils/sphinx.py
skel/default.prmpt
skel/elite.prmpt
skel/prmpt.cfg
skel/red.prmpt
skel/simple1.prmpt
skel/functions/example.py
test/test_colours.py
test/test_functionContainer.py
test/test_functions.py
test/test_parser.py
test/test_prmpt.py
test/test_skel.py
test/test_vcs.py