Metadata-Version: 2.1
Name: prmpt
Version: 0.5.0
Summary: A command line prompt markup language
Home-page: https://github.com/ltn100/prmpt
Author: Lee Netherton
Author-email: lee.netherton@gmail.com
License: MIT licence, see LICENCE
Classifier: License :: OSI Approved :: MIT License
Classifier: Programming Language :: Python
Classifier: Programming Language :: Python :: 2
Classifier: Programming Language :: Python :: 3
Classifier: Topic :: Software Development
Classifier: Topic :: Software Development :: User Interfaces
Classifier: Topic :: System :: Shells
Classifier: Topic :: System :: System Shells
Classifier: Topic :: Terminals
Classifier: Topic :: Terminals :: Terminal Emulators/X Terminals
Classifier: Topic :: Utilities
Classifier: Operating System :: POSIX
Classifier: Operating System :: POSIX :: Linux
Classifier: Operating System :: Unix
Classifier: Operating System :: MacOS
License-File: LICENSE
